dfx_apiv2_client/Auths.py
dfx_apiv2_client/Base.py
dfx_apiv2_client/Devices.py
dfx_apiv2_client/General.py
dfx_apiv2_client/Licenses.py
dfx_apiv2_client/Measurements.py
dfx_apiv2_client/Organizations.py
dfx_apiv2_client/Profiles.py
dfx_apiv2_client/Settings.py
dfx_apiv2_client/Studies.py
dfx_apiv2_client/Users.py
dfx_apiv2_client/__init__.py
dfx_apiv2_client-0.15.0.dist-info/LICENSE.txt
dfx_apiv2_client-0.15.0.dist-info/METADATA
dfx_apiv2_client-0.15.0.dist-info/WHEEL
dfx_apiv2_client-0.15.0.dist-info/top_level.txt
dfx_apiv2_client-0.15.0.dist-info/RECORD
