Metadata-Version: 2.1
Name: dfx-apiv2-client
Version: 0.15.0
Summary: dfx-apiv2-client is a Python 3 asyncio client library for the Nuralogix DeepAffex API.
Home-page: https://github.com/nuralogix/dfx-apiv2-client-py
Author: NuraLogix Corporation
Classifier: Programming Language :: Python :: 3
Classifier: License :: OSI Approved :: MIT License
Classifier: Operating System :: OS Independent
Classifier: Intended Audience :: Developers
License-File: LICENSE.txt
Requires-Dist: aiohttp <4
